{
    "3616": {
        "lootItemsType": {
            "weapon": {
                "Two Handed Sword": 100,
                "Two Handed Halberd": 100,
                "One Handed Sword": 100,
                "One Handed Axe": 100,
                "One Handed Blunt": 100,
                "Wand": 100,
                "Staff": 100,
                "Dagger": 100,
                "Rapier": 100,
                "Karon": 100,
                "Xenon": 100,
                "Crossbow": 100,
                "Bow": 100,
                "Chakram": 100,
                "Kataria": 100
            },
            "armor": {
                "Chest": 100,
                "Feet": 100,
                "Hands": 100,
                "Head": 100,
                "Legs": 100,
                "Shield": 100
            },
            "accessory": {
                "Accessory": 100
            }
        },
        "lootItemRarityTypes": ["elite_item"],
        "lootMiscTypes": {"elemental_stone": 3, "scroll": 100, "potion": 100},
        "gold": {
            "min": 1000,
            "max": 2000
        }
    },
    "3617": {
        "lootItemsType": {
            "weapon": {
                "Two Handed Sword": 100,
                "Two Handed Halberd": 100,
                "One Handed Sword": 100,
                "One Handed Axe": 100,
                "One Handed Blunt": 100,
                "Wand": 100,
                "Staff": 100,
                "Dagger": 100,
                "Rapier": 100,
                "Karon": 100,
                "Xenon": 100,
                "Crossbow": 100,
                "Bow": 100,
                "Chakram": 100,
                "Kataria": 100
            },
            "armor": {
                "Chest": 100,
                "Feet": 100,
                "Hands": 100,
                "Head": 100,
                "Legs": 100,
                "Shield": 100
            },
            "accessory": {
                "Accessory": 100
            }
        },
        "lootItemRarityTypes": ["rare_item"],
        "lootMiscTypes": {"elemental_stone": 3, "combination_material": 1, "scroll": 100, "potion": 100},
        "gold": {
            "min": 1000,
            "max": 2000
        }
    }
}